caic/__init__.py
caic/utils/__init__.py
caic/utils/cjson.py
caic/utils/logger.py
caic/utils/utils.py
pyaic/__init__.py
pyaic/scripts/__init__.py
pyaic/scripts/gen_paper_md.py
pyaic/tests/__init__.py
pyaic/translate/__init__.py
pyaic/translate/haici.py
pyaic/utils/__init__.py
pyaic/utils/cjson.py
pyaic/utils/logger.py
pyaic/utils/pdf2words.py
pyaic/utils/utils.py
python_aic-0.1.10.dist-info/METADATA
python_aic-0.1.10.dist-info/WHEEL
python_aic-0.1.10.dist-info/top_level.txt
python_aic-0.1.10.dist-info/RECORD
