Metadata-Version: 2.1
Name: python-aic
Version: 0.1.10
Summary: This is a pyaic project package.
Home-page: http://www.cbguo.com
Author: Bangguo Chen
Author-email: mail@cbguo.com
